imiit_student_bot/__init__.py
imiit_student_bot/__main__.py
imiit_student_bot/py.typed
imiit_student_bot/response.json
imiit_student_bot-1.0.0.dist-info/entry_points.txt
imiit_student_bot-1.0.0.dist-info/LICENSE.rst
imiit_student_bot-1.0.0.dist-info/WHEEL
imiit_student_bot-1.0.0.dist-info/METADATA
imiit_student_bot-1.0.0.dist-info/RECORD
