Metadata-Version: 2.1
Name: imiit-student-bot
Version: 1.0.0
Summary: Imiit Student Bot
Home-page: https://github.com/nikolai-in/imiit-student-bot
License: GPL-3.0
Author: Николай Иванов
Author-email: nikolai.in@tuta.io
Requires-Python: >=3.7,<4.0
Classifier: Development Status :: 2 - Pre-Alpha
Classifier: License :: OSI Approved :: GNU General Public License v3 (GPLv3)
Classifier: Programming Language :: Python :: 3
Classifier: Programming Language :: Python :: 3.10
Classifier: Programming Language :: Python :: 3.7
Classifier: Programming Language :: Python :: 3.8
Classifier: Programming Language :: Python :: 3.9
Requires-Dist: click (>=8.0.1,<9.0.0)
Requires-Dist: python-telegram-bot (>=13.8.1,<14.0.0)
Project-URL: Changelog, https://github.com/nikolai-in/imiit-student-bot/releases
Project-URL: Documentation, https://imiit-student-bot.readthedocs.io
Project-URL: Repository, https://github.com/nikolai-in/imiit-student-bot
